pyinsee/__init__.py
pyinsee/_version.py
pyinsee/config.py
pyinsee/insee_cli.py
pyinsee/insee_client.py
pyinsee/logger.py
pyinsee/setup_cli.py
pyinsee/utils.py
tests/__init__.py
pyinsee-0.1.4.dist-info/LICENSE
pyinsee-0.1.4.dist-info/METADATA
pyinsee-0.1.4.dist-info/WHEEL
pyinsee-0.1.4.dist-info/entry_points.txt
pyinsee-0.1.4.dist-info/top_level.txt
pyinsee-0.1.4.dist-info/RECORD
