Metadata-Version: 2.1
Name: pyinsee
Version: 0.1.4
Summary: A package for collecting and processing company data from INSEE API
Author: Ayman KUMA
Author-email: Ayman KUMA <aymankamel.mail@example.com>
License:                                  Apache License
Project-URL: Homepage, https://github.com/AymanKUMA/insee-client
Keywords: insee,api,company data
Classifier: License :: OSI Approved :: Apache Software License
Classifier: Programming Language :: Python
Classifier: Programming Language :: Python :: 3
Requires-Python: >=3.8
License-File: LICENSE
Requires-Dist: requests
Requires-Dist: python-dotenv
